bigbluebutton/__init__.py
bigbluebutton/api/__init__.py
bigbluebutton/api/_caching.py
bigbluebutton/api/attendee.py
bigbluebutton/api/bigbluebutton.py
bigbluebutton/api/loadbalancing.py
bigbluebutton/api/meeting.py
bigbluebutton/api/util.py
bigbluebutton/cli/__init__.py
bigbluebutton/django/__init__.py
bigbluebutton/django/admin.py
bigbluebutton/django/apps.py
bigbluebutton/django/migrations/0001_initial.py
bigbluebutton/django/migrations/0002_auto_20201009_1437.py
bigbluebutton/django/migrations/__init__.py
bigbluebutton/django/models.py
bigbluebutton/django/settings.py
bigbluebutton/django/urls.py
bigbluebutton/django/util.py
bigbluebutton/django/views.py
bigbluebutton2-0.1a9.dist-info/entry_points.txt
bigbluebutton2-0.1a9.dist-info/LICENSE
bigbluebutton2-0.1a9.dist-info/WHEEL
bigbluebutton2-0.1a9.dist-info/METADATA
bigbluebutton2-0.1a9.dist-info/RECORD
